choumine_test5/__init__.py
choumine_test5/__main__.py
choumine_test5/common.py
choumine_test5/tools.py
choumine_test5-0.1.0.dist-info/METADATA
choumine_test5-0.1.0.dist-info/WHEEL
choumine_test5-0.1.0.dist-info/entry_points.txt
choumine_test5-0.1.0.dist-info/RECORD
